{
  "headers": [
    "名称",
    "地点",
    "图片",
    "内容介绍",
    "文化起源",
    "故事介绍",
    "非遗寓意",
    "非遗材料",
    "视频超链接",
    null,
    null
  ],
  "totalRows": 172,
  "videoRowCount": 142,
  "hyperlinksInXml": {},
  "sampleRows": [
    {
      "row": 3,
      "name": "汉剧",
      "location": "湖北武汉",
      "videoText": "【汉剧《宇宙锋》，武汉汉剧院，耿丽亚、朱勇、汪晶、范琼 、曾纯等，2025.06.26直播回放，第四届全国戏曲(南方片)会演-哔哩哔哩】 https://b23.tv/JqB4N7K",
      "videoLinks": [],
      "videoUrlsFromText": [
        "https://b23.tv/JqB4N7K"
      ]
    },
    {
      "row": 4,
      "name": "土家族摆手舞",
      "location": "恩施土家族苗族自治州来凤县",
      "videoText": "【《舞韵织梦》土家族摆手舞微视频-哔哩哔哩】 https://b23.tv/9NQaf4s",
      "videoLinks": [],
      "videoUrlsFromText": [
        "https://b23.tv/9NQaf4s"
      ]
    },
    {
      "row": 5,
      "name": "黄梅戏",
      "location": "黄冈黄梅县",
      "videoText": "【黄梅戏《女驸马》韩再芬 吴美莲 1080p 安徽再芬黄梅艺术剧院 春节黄梅戏优秀剧目公益性展播2026.02.16-哔哩哔哩】 https://b23.tv/XL9WpyA",
      "videoLinks": [],
      "videoUrlsFromText": [
        "https://b23.tv/XL9WpyA"
      ]
    },
    {
      "row": 6,
      "name": "西兰卡普",
      "location": "恩施土家族苗族自治州",
      "videoText": "【土家之花——西兰卡普-哔哩哔哩】 https://b23.tv/tmlYLGA",
      "videoLinks": [],
      "videoUrlsFromText": [
        "https://b23.tv/tmlYLGA"
      ]
    },
    {
      "row": 7,
      "name": "武当武术",
      "location": "十堰市",
      "videoText": "【【非遗里的中国】武当武术-哔哩哔哩】 https://b23.tv/oMQ3Bt5",
      "videoLinks": [],
      "videoUrlsFromText": [
        "https://b23.tv/oMQ3Bt5"
      ]
    },
    {
      "row": 8,
      "name": "北京",
      "location": null,
      "videoText": null,
      "videoLinks": []
    },
    {
      "row": 9,
      "name": "景泰蓝",
      "location": "北京市",
      "videoText": "【【2025 】景泰蓝艺术博物馆（北京 · ）【云游直播回放】-溜达搬运-哔哩哔哩】 https://b23.tv/Y3fbIyT",
      "videoLinks": [],
      "videoUrlsFromText": [
        "https://b23.tv/Y3fbIyT"
      ]
    },
    {
      "row": 10,
      "name": "京剧",
      "location": "北京市",
      "videoText": "【【京剧】 来来来，带你看看不一样的京剧宣传片-哔哩哔哩】 https://b23.tv/R6NnFAW",
      "videoLinks": [],
      "videoUrlsFromText": [
        "https://b23.tv/R6NnFAW"
      ]
    },
    {
      "row": 11,
      "name": "兔儿爷彩绘",
      "location": "北京市",
      "videoText": "【第 421 集《北京兔儿爷彩绘：陶土与颜料的童趣香》-哔哩哔哩】 https://b23.tv/xOp6f0w",
      "videoLinks": [],
      "videoUrlsFromText": [
        "https://b23.tv/xOp6f0w"
      ]
    },
    {
      "row": 12,
      "name": "花丝镶嵌",
      "location": "北京市",
      "videoText": "【“燕京八绝”之首的花丝镶嵌，曾为皇家高定，秒杀一切奢侈品-哔哩哔哩】 https://b23.tv/PgGRWIq",
      "videoLinks": [],
      "videoUrlsFromText": [
        "https://b23.tv/PgGRWIq"
      ]
    },
    {
      "row": 13,
      "name": "北京雕漆",
      "location": "北京市",
      "videoText": "【燕京八绝：千年朱红盛宴，非遗文氏雕漆，用时间置换的艺术珍品-哔哩哔哩】 https://b23.tv/lnGbWTO",
      "videoLinks": [],
      "videoUrlsFromText": [
        "https://b23.tv/lnGbWTO"
      ]
    },
    {
      "row": 15,
      "name": "昆曲",
      "location": "昆山市",
      "videoText": "【昆曲：三分钟品味600年昆曲之美|江苏文化名片-哔哩哔哩】 https://b23.tv/Ki1qtuJ",
      "videoLinks": [],
      "videoUrlsFromText": [
        "https://b23.tv/Ki1qtuJ"
      ]
    },
    {
      "row": 16,
      "name": "苏绣",
      "location": "苏州市",
      "videoText": "【何以中国第十七期：苏绣流芳-哔哩哔哩】 https://b23.tv/OpaPGyO",
      "videoLinks": [],
      "videoUrlsFromText": [
        "https://b23.tv/OpaPGyO"
      ]
    },
    {
      "row": 17,
      "name": "云锦",
      "location": "南京市",
      "videoText": "【南京云锦-哔哩哔哩】 https://b23.tv/WWhitnP",
      "videoLinks": [],
      "videoUrlsFromText": [
        "https://b23.tv/WWhitnP"
      ]
    },
    {
      "row": 18,
      "name": "香山帮传统建筑营造技艺",
      "location": "苏州吴中区胥口镇香山（太湖之滨）",
      "videoText": "【香山帮木作传统营造技艺的信息可视化动态效果演示-哔哩哔哩】 https://b23.tv/avIqMsh",
      "videoLinks": [],
      "videoUrlsFromText": [
        "https://b23.tv/avIqMsh"
      ]
    },
    {
      "row": 19,
      "name": "吴门琴派",
      "location": "苏州古城（姑苏区）",
      "videoText": "【纪录片《吴门琴话》百年琴韵 琴脉在兹-哔哩哔哩】 https://b23.tv/jiCiAKS",
      "videoLinks": [],
      "videoUrlsFromText": [
        "https://b23.tv/jiCiAKS"
      ]
    },
    {
      "row": 21,
      "name": "傣族孔雀舞（传统舞蹈・第一批国家级非遗）",
      "location": "云南省德宏州瑞丽市",
      "videoText": "【傣族孔雀舞——《中国影像方志》云南卷芒市篇 传承记-哔哩哔哩】 https://b23.tv/YsBRrNX",
      "videoLinks": [],
      "videoUrlsFromText": [
        "https://b23.tv/YsBRrNX"
      ]
    },
    {
      "row": 22,
      "name": "白族扎染技艺",
      "location": "云南省大理市周城镇",
      "videoText": "【“扎染”大理白族传统非遗｜自制纪录短片-哔哩哔哩】 https://b23.tv/TGoMdpt",
      "videoLinks": [],
      "videoUrlsFromText": [
        "https://b23.tv/TGoMdpt"
      ]
    },
    {
      "row": 23,
      "name": "建水紫陶烧制技艺",
      "location": "云南省红河州建水县碗窑村",
      "videoText": "【建水紫陶——因艺而珍，因文而雅-哔哩哔哩】 https://b23.tv/Lam2wm0",
      "videoLinks": [],
      "videoUrlsFromText": [
        "https://b23.tv/Lam2wm0"
      ]
    },
    {
      "row": 24,
      "name": "景颇族目瑙纵歌",
      "location": "云南省德宏州陇川县",
      "videoText": "【官方版《目瑙纵歌》，最正宗的版本，多角度场景体现，分享给所有朋友！#德宏陇川#景颇族#目瑙纵歌-哔哩哔哩】 https://b23.tv/KiT5yfJ",
      "videoLinks": [],
      "videoUrlsFromText": [
        "https://b23.tv/KiT5yfJ"
      ]
    },
    {
      "row": 25,
      "name": "普洱茶制作技艺",
      "location": "云南省普洱市、西双版纳勐海县",
      "videoText": "【普洱茶制作技艺-国家级非物质文化遗产代表性项目-哔哩哔哩】 https://b23.tv/IjO2NSA",
      "videoLinks": [],
      "videoUrlsFromText": [
        "https://b23.tv/IjO2NSA"
      ]
    },
    {
      "row": 27,
      "name": "宣纸传统制作技艺",
      "location": "安徽省宣城市泾县",
      "videoText": "【探寻:宣纸千年的秘密, 《遇见非遗 走近宣纸》#校地携手·智汇宣城-哔哩哔哩】 https://b23.tv/wMyIsx3",
      "videoLinks": [],
      "videoUrlsFromText": [
        "https://b23.tv/wMyIsx3"
      ]
    },
    {
      "row": 28,
      "name": "芜湖铁画锻制技艺",
      "location": "安徽省芜湖市",
      "videoText": "【铁骨画魂——芜湖铁画的活态传承-哔哩哔哩】 https://b23.tv/1luXDCI",
      "videoLinks": [],
      "videoUrlsFromText": [
        "https://b23.tv/1luXDCI"
      ]
    },
    {
      "row": 29,
      "name": "祁门红茶制作技艺",
      "location": "安徽省黄山市祁门县",
      "videoText": "【CCTV《非遗里的中国》第三季技艺小片——红茶制作技艺（祁门红茶制作技艺）-哔哩哔哩】 https://b23.tv/H53cceX",
      "videoLinks": [],
      "videoUrlsFromText": [
        "https://b23.tv/H53cceX"
      ]
    },
    {
      "row": 30,
      "name": "凤阳花鼓",
      "location": "安徽省滁州市凤阳县",
      "videoText": "【【非遗】【凤阳花鼓】你 会 跳 舞 吗 ？-哔哩哔哩】 https://b23.tv/0pobLh8",
      "videoLinks": [],
      "videoUrlsFromText": [
        "https://b23.tv/0pobLh8"
      ]
    }
  ],
  "videoRows": [
    {
      "row": 3,
      "name": "汉剧",
      "location": "湖北武汉",
      "videoText": "【汉剧《宇宙锋》，武汉汉剧院，耿丽亚、朱勇、汪晶、范琼 、曾纯等，2025.06.26直播回放，第四届全国戏曲(南方片)会演-哔哩哔哩】 https://b23.tv/JqB4N7K",
      "videoLinks": [],
      "videoUrlsFromText": [
        "https://b23.tv/JqB4N7K"
      ]
    },
    {
      "row": 4,
      "name": "土家族摆手舞",
      "location": "恩施土家族苗族自治州来凤县",
      "videoText": "【《舞韵织梦》土家族摆手舞微视频-哔哩哔哩】 https://b23.tv/9NQaf4s",
      "videoLinks": [],
      "videoUrlsFromText": [
        "https://b23.tv/9NQaf4s"
      ]
    },
    {
      "row": 5,
      "name": "黄梅戏",
      "location": "黄冈黄梅县",
      "videoText": "【黄梅戏《女驸马》韩再芬 吴美莲 1080p 安徽再芬黄梅艺术剧院 春节黄梅戏优秀剧目公益性展播2026.02.16-哔哩哔哩】 https://b23.tv/XL9WpyA",
      "videoLinks": [],
      "videoUrlsFromText": [
        "https://b23.tv/XL9WpyA"
      ]
    },
    {
      "row": 6,
      "name": "西兰卡普",
      "location": "恩施土家族苗族自治州",
      "videoText": "【土家之花——西兰卡普-哔哩哔哩】 https://b23.tv/tmlYLGA",
      "videoLinks": [],
      "videoUrlsFromText": [
        "https://b23.tv/tmlYLGA"
      ]
    },
    {
      "row": 7,
      "name": "武当武术",
      "location": "十堰市",
      "videoText": "【【非遗里的中国】武当武术-哔哩哔哩】 https://b23.tv/oMQ3Bt5",
      "videoLinks": [],
      "videoUrlsFromText": [
        "https://b23.tv/oMQ3Bt5"
      ]
    },
    {
      "row": 9,
      "name": "景泰蓝",
      "location": "北京市",
      "videoText": "【【2025 】景泰蓝艺术博物馆（北京 · ）【云游直播回放】-溜达搬运-哔哩哔哩】 https://b23.tv/Y3fbIyT",
      "videoLinks": [],
      "videoUrlsFromText": [
        "https://b23.tv/Y3fbIyT"
      ]
    },
    {
      "row": 10,
      "name": "京剧",
      "location": "北京市",
      "videoText": "【【京剧】 来来来，带你看看不一样的京剧宣传片-哔哩哔哩】 https://b23.tv/R6NnFAW",
      "videoLinks": [],
      "videoUrlsFromText": [
        "https://b23.tv/R6NnFAW"
      ]
    },
    {
      "row": 11,
      "name": "兔儿爷彩绘",
      "location": "北京市",
      "videoText": "【第 421 集《北京兔儿爷彩绘：陶土与颜料的童趣香》-哔哩哔哩】 https://b23.tv/xOp6f0w",
      "videoLinks": [],
      "videoUrlsFromText": [
        "https://b23.tv/xOp6f0w"
      ]
    },
    {
      "row": 12,
      "name": "花丝镶嵌",
      "location": "北京市",
      "videoText": "【“燕京八绝”之首的花丝镶嵌，曾为皇家高定，秒杀一切奢侈品-哔哩哔哩】 https://b23.tv/PgGRWIq",
      "videoLinks": [],
      "videoUrlsFromText": [
        "https://b23.tv/PgGRWIq"
      ]
    },
    {
      "row": 13,
      "name": "北京雕漆",
      "location": "北京市",
      "videoText": "【燕京八绝：千年朱红盛宴，非遗文氏雕漆，用时间置换的艺术珍品-哔哩哔哩】 https://b23.tv/lnGbWTO",
      "videoLinks": [],
      "videoUrlsFromText": [
        "https://b23.tv/lnGbWTO"
      ]
    },
    {
      "row": 15,
      "name": "昆曲",
      "location": "昆山市",
      "videoText": "【昆曲：三分钟品味600年昆曲之美|江苏文化名片-哔哩哔哩】 https://b23.tv/Ki1qtuJ",
      "videoLinks": [],
      "videoUrlsFromText": [
        "https://b23.tv/Ki1qtuJ"
      ]
    },
    {
      "row": 16,
      "name": "苏绣",
      "location": "苏州市",
      "videoText": "【何以中国第十七期：苏绣流芳-哔哩哔哩】 https://b23.tv/OpaPGyO",
      "videoLinks": [],
      "videoUrlsFromText": [
        "https://b23.tv/OpaPGyO"
      ]
    },
    {
      "row": 17,
      "name": "云锦",
      "location": "南京市",
      "videoText": "【南京云锦-哔哩哔哩】 https://b23.tv/WWhitnP",
      "videoLinks": [],
      "videoUrlsFromText": [
        "https://b23.tv/WWhitnP"
      ]
    },
    {
      "row": 18,
      "name": "香山帮传统建筑营造技艺",
      "location": "苏州吴中区胥口镇香山（太湖之滨）",
      "videoText": "【香山帮木作传统营造技艺的信息可视化动态效果演示-哔哩哔哩】 https://b23.tv/avIqMsh",
      "videoLinks": [],
      "videoUrlsFromText": [
        "https://b23.tv/avIqMsh"
      ]
    },
    {
      "row": 19,
      "name": "吴门琴派",
      "location": "苏州古城（姑苏区）",
      "videoText": "【纪录片《吴门琴话》百年琴韵 琴脉在兹-哔哩哔哩】 https://b23.tv/jiCiAKS",
      "videoLinks": [],
      "videoUrlsFromText": [
        "https://b23.tv/jiCiAKS"
      ]
    },
    {
      "row": 21,
      "name": "傣族孔雀舞（传统舞蹈・第一批国家级非遗）",
      "location": "云南省德宏州瑞丽市",
      "videoText": "【傣族孔雀舞——《中国影像方志》云南卷芒市篇 传承记-哔哩哔哩】 https://b23.tv/YsBRrNX",
      "videoLinks": [],
      "videoUrlsFromText": [
        "https://b23.tv/YsBRrNX"
      ]
    },
    {
      "row": 22,
      "name": "白族扎染技艺",
      "location": "云南省大理市周城镇",
      "videoText": "【“扎染”大理白族传统非遗｜自制纪录短片-哔哩哔哩】 https://b23.tv/TGoMdpt",
      "videoLinks": [],
      "videoUrlsFromText": [
        "https://b23.tv/TGoMdpt"
      ]
    },
    {
      "row": 23,
      "name": "建水紫陶烧制技艺",
      "location": "云南省红河州建水县碗窑村",
      "videoText": "【建水紫陶——因艺而珍，因文而雅-哔哩哔哩】 https://b23.tv/Lam2wm0",
      "videoLinks": [],
      "videoUrlsFromText": [
        "https://b23.tv/Lam2wm0"
      ]
    },
    {
      "row": 24,
      "name": "景颇族目瑙纵歌",
      "location": "云南省德宏州陇川县",
      "videoText": "【官方版《目瑙纵歌》，最正宗的版本，多角度场景体现，分享给所有朋友！#德宏陇川#景颇族#目瑙纵歌-哔哩哔哩】 https://b23.tv/KiT5yfJ",
      "videoLinks": [],
      "videoUrlsFromText": [
        "https://b23.tv/KiT5yfJ"
      ]
    },
    {
      "row": 25,
      "name": "普洱茶制作技艺",
      "location": "云南省普洱市、西双版纳勐海县",
      "videoText": "【普洱茶制作技艺-国家级非物质文化遗产代表性项目-哔哩哔哩】 https://b23.tv/IjO2NSA",
      "videoLinks": [],
      "videoUrlsFromText": [
        "https://b23.tv/IjO2NSA"
      ]
    },
    {
      "row": 27,
      "name": "宣纸传统制作技艺",
      "location": "安徽省宣城市泾县",
      "videoText": "【探寻:宣纸千年的秘密, 《遇见非遗 走近宣纸》#校地携手·智汇宣城-哔哩哔哩】 https://b23.tv/wMyIsx3",
      "videoLinks": [],
      "videoUrlsFromText": [
        "https://b23.tv/wMyIsx3"
      ]
    },
    {
      "row": 28,
      "name": "芜湖铁画锻制技艺",
      "location": "安徽省芜湖市",
      "videoText": "【铁骨画魂——芜湖铁画的活态传承-哔哩哔哩】 https://b23.tv/1luXDCI",
      "videoLinks": [],
      "videoUrlsFromText": [
        "https://b23.tv/1luXDCI"
      ]
    },
    {
      "row": 29,
      "name": "祁门红茶制作技艺",
      "location": "安徽省黄山市祁门县",
      "videoText": "【CCTV《非遗里的中国》第三季技艺小片——红茶制作技艺（祁门红茶制作技艺）-哔哩哔哩】 https://b23.tv/H53cceX",
      "videoLinks": [],
      "videoUrlsFromText": [
        "https://b23.tv/H53cceX"
      ]
    },
    {
      "row": 30,
      "name": "凤阳花鼓",
      "location": "安徽省滁州市凤阳县",
      "videoText": "【【非遗】【凤阳花鼓】你 会 跳 舞 吗 ？-哔哩哔哩】 https://b23.tv/0pobLh8",
      "videoLinks": [],
      "videoUrlsFromText": [
        "https://b23.tv/0pobLh8"
      ]
    },
    {
      "row": 31,
      "name": "徽墨制作技艺",
      "location": "安徽省黄山市歙县",
      "videoText": "【【徽墨】闻名中外的“文房四宝”-哔哩哔哩】 https://b23.tv/W4IADaR",
      "videoLinks": [],
      "videoUrlsFromText": [
        "https://b23.tv/W4IADaR"
      ]
    },
    {
      "row": 32,
      "name": "无为鱼灯（灯舞）",
      "location": "安徽省芜湖市无为市",
      "videoText": "【非遗-无为鱼灯-哔哩哔哩】 https://b23.tv/x2VElSN",
      "videoLinks": [],
      "videoUrlsFromText": [
        "https://b23.tv/x2VElSN"
      ]
    },
    {
      "row": 34,
      "name": "济南面塑",
      "location": "山东省济南市",
      "videoText": "【非遗传承-济南面塑-哔哩哔哩】 https://b23.tv/VpIflkZ",
      "videoLinks": [],
      "videoUrlsFromText": [
        "https://b23.tv/VpIflkZ"
      ]
    },
    {
      "row": 35,
      "name": "胶州秧歌",
      "location": "山东省青岛市",
      "videoText": "【【北京舞蹈学院/王雪柔】山东秧歌《孤月杳然》Moon in the Mood-哔哩哔哩】 https://b23.tv/ODn3CsL",
      "videoLinks": [],
      "videoUrlsFromText": [
        "https://b23.tv/ODn3CsL"
      ]
    },
    {
      "row": 36,
      "name": "博山琉璃烧制技艺",
      "location": "山东省淄博市",
      "videoText": "【非遗琉璃专题片《遇见琉璃》-哔哩哔哩】 https://b23.tv/6ajpI9s",
      "videoLinks": [],
      "videoUrlsFromText": [
        "https://b23.tv/6ajpI9s"
      ]
    },
    {
      "row": 37,
      "name": "威海锡镶技艺",
      "location": "山东省威海市",
      "videoText": "【【非遗探秘】威海锡镶技艺：百年匠心，金属与陶瓷的绝美交响-哔哩哔哩】 https://b23.tv/KbPUZdh",
      "videoLinks": [],
      "videoUrlsFromText": [
        "https://b23.tv/KbPUZdh"
      ]
    }
  ]
}